{"type":"FeatureCollection", "features": [
{"type":"Feature","geometry":{"type":"Point","coordinates":[116.32869488900008,39.90614226100007]},"properties":{"OBJECTID":1,"岗位名称":"木樨地桥上","警力数":"1","单位":"交通支队"}},
{"type":"Feature","geometry":{"type":"Point","coordinates":[116.3232832000001,39.90614499000003]},"properties":{"OBJECTID":2,"岗位名称":"木樨地桥西","警力数":"1","单位":"交通支队"}},
{"type":"Feature","geometry":{"type":"Point","coordinates":[116.32273700000007,39.90640100000007]},"properties":{"OBJECTID":3,"岗位名称":"北蜂窝路","警力数":"1","单位":"交通支队"}},
{"type":"Feature","geometry":{"type":"Point","coordinates":[116.32197630500002,39.90640674100007]},"properties":{"OBJECTID":4,"岗位名称":"军委东南门","警力数":"1","单位":"交通支队"}},
{"type":"Feature","geometry":{"type":"Point","coordinates":[116.32094815700009,39.90642006300004]},"properties":{"OBJECTID":5,"岗位名称":"军委南门","警力数":"1","单位":"交通支队"}},
{"type":"Feature","geometry":{"type":"Point","coordinates":[116.31922599300003,39.90643086100005]},"properties":{"OBJECTID":6,"岗位名称":"军博红绿灯","警力数":"3","单位":"交通支队"}},
{"type":"Feature","geometry":{"type":"Point","coordinates":[116.31695732500009,39.90663897300004]},"properties":{"OBJECTID":7,"岗位名称":"军博广场","警力数":"1","单位":"交通支队"}},
{"type":"Feature","geometry":{"type":"Point","coordinates":[116.3151513140001,39.90641054500003]},"properties":{"OBJECTID":8,"岗位名称":"世纪坛路口","警力数":"6","单位":"交通支队"}},
{"type":"Feature","geometry":{"type":"Point","coordinates":[116.31238288500003,39.90648681500005]},"properties":{"OBJECTID":9,"岗位名称":"京西北门对面","警力数":"1","单位":"交通支队"}},
{"type":"Feature","geometry":{"type":"Point","coordinates":[116.3106461000001,39.90650202000006]},"properties":{"OBJECTID":10,"岗位名称":"京西路口","警力数":"6","单位":"交通支队"}},
{"type":"Feature","geometry":{"type":"Point","coordinates":[116.3147965170001,39.90592905300008]},"properties":{"OBJECTID":11,"岗位名称":"京东岗备勤","警力数":"5","单位":"交通支队"}},
{"type":"Feature","geometry":{"type":"Point","coordinates":[116.30947810200007,39.906088683000064]},"properties":{"OBJECTID":12,"岗位名称":"科苑过街天桥","警力数":"1","单位":"交通支队"}},
{"type":"Feature","geometry":{"type":"Point","coordinates":[116.31067000000007,39.90982100000008]},"properties":{"OBJECTID":13,"岗位名称":"柳林馆路与玉渊潭南路交叉口","警力数":"1","单位":"交通支队"}},
{"type":"Feature","geometry":{"type":"Point","coordinates":[116.31064552700002,39.90762239700007]},"properties":{"OBJECTID":14,"岗位名称":"央视西门","警力数":"1","单位":"交通支队"}},
{"type":"Feature","geometry":{"type":"Point","coordinates":[116.31522108700005,39.90977150100008]},"properties":{"OBJECTID":15,"岗位名称":"世纪坛桥下","警力数":"1","单位":"交通支队"}},
{"type":"Feature","geometry":{"type":"Point","coordinates":[116.31063800000004,39.90227200000004]},"properties":{"OBJECTID":16,"岗位名称":"空军大院东门","警力数":"1","单位":"交通支队"}},
{"type":"Feature","geometry":{"type":"Point","coordinates":[116.31065101500008,39.89950067400008]},"properties":{"OBJECTID":17,"岗位名称":"空军大院东南门","警力数":"1","单位":"交通支队"}},
{"type":"Feature","geometry":{"type":"Point","coordinates":[116.30662397600008,39.907321341000056]},"properties":{"OBJECTID":18,"岗位名称":"国海广场","警力数":"1","单位":"交通支队"}},
{"type":"Feature","geometry":{"type":"Point","coordinates":[116.3149049000001,39.89912103000006]},"properties":{"OBJECTID":19,"岗位名称":"铁医路东口","警力数":"1","单位":"交通支队"}},
{"type":"Feature","geometry":{"type":"Point","coordinates":[116.32809905700003,39.90590039800003]},"properties":{"OBJECTID":20,"岗位名称":"木樨地桥西","警力数":"1","单位":"交通支队"}},
{"type":"Feature","geometry":{"type":"Point","coordinates":[116.3068313550001,39.905187589000036]},"properties":{"OBJECTID":21,"岗位名称":"新兴桥东南角","警力数":"1","单位":"交通支队"}},
{"type":"Feature","geometry":{"type":"Point","coordinates":[116.31485391800004,39.90757979400007]},"properties":{"OBJECTID":22,"岗位名称":"央视东门","警力数":"1","单位":"交通支队"}},
{"type":"Feature","geometry":{"type":"Point","coordinates":[116.30672616400011,39.906926578000025]},"properties":{"OBJECTID":23,"岗位名称":"新兴桥北向东匝道","警力数":"1","单位":"交通支队"}},
{"type":"Feature","geometry":{"type":"Point","coordinates":[116.30692143200008,39.90555973900007]},"properties":{"OBJECTID":24,"岗位名称":"新兴桥南向东匝道","警力数":"1","单位":"交通支队"}},
{"type":"Feature","geometry":{"type":"Point","coordinates":[116.31513550500006,39.90592178600008]},"properties":{"OBJECTID":25,"岗位名称":"世纪坛路口南侧","警力数":"1","单位":"交通支队"}},
{"type":"Feature","geometry":{"type":"Point","coordinates":[116.32275286600009,39.90786107900004]},"properties":{"OBJECTID":26,"岗位名称":"军委东门","警力数":"1","单位":"交通支队"}},
{"type":"Feature","geometry":{"type":"Point","coordinates":[116.30906531200003,39.906148649000045]},"properties":{"OBJECTID":27,"岗位名称":"新兴桥南向东与复兴路交叉口","警力数":"2","单位":"交通支队"}}
]}