[{"岗位编号":1,"姓名":"于洋","职务":"队长","电话":"19810258097","电台":"","执勤时段":""},{"岗位编号":1,"姓名":"熊梦龙","职务":"队长","电话":"19810258797","电台":"","执勤时段":""},{"岗位编号":2,"姓名":" 康子英","职务":"民警","电话":"19810258073","电台":"","执勤时段":""},{"岗位编号":2,"姓名":"陈哲","职务":"民警","电话":"19810258091","电台":"","执勤时段":""},{"岗位编号":3,"姓名":"高立成","职务":"民警","电话":"19810258078","电台":"","执勤时段":""},{"岗位编号":3,"姓名":"刘新庆","职务":"民警","电话":"19810258066","电台":"","执勤时段":""},{"岗位编号":4,"姓名":"付培锋","职务":"民警","电话":"19810258063","电台":"","执勤时段":""},{"岗位编号":5,"姓名":"刘震一","职务":"副主任","电话":"19810258116","电台":"","执勤时段":""},{"岗位编号":6,"姓名":"郑卫波","职务":"队长","电话":"19810219385","电台":"","执勤时段":""},{"岗位编号":7,"姓名":"杨润根","职务":"副队长","电话":"19810259578","电台":"","执勤时段":""},{"岗位编号":8,"姓名":"李享","职务":"副队长","电话":"19810258920","电台":"","执勤时段":""},{"岗位编号":8,"姓名":"朱立锋","职务":"队长","电话":"19810258583","电台":"","执勤时段":""},{"岗位编号":9,"姓名":"张迎新","职务":"民警","电话":"18518857575","电台":"","执勤时段":""},{"岗位编号":10,"姓名":"王冰","职务":"民警","电话":"19810259542","电台":"","执勤时段":""},{"岗位编号":11,"姓名":"王之元","职务":"民警","电话":"19810259468","电台":"","执勤时段":""},{"岗位编号":12,"姓名":"陈宝全","职务":"民警","电话":"19810259545","电台":"","执勤时段":""},{"岗位编号":13,"姓名":"石立斌","职务":"民警","电话":"19810259820","电台":"","执勤时段":""},{"岗位编号":14,"姓名":"李建军","职务":"民警","电话":"19810257749","电台":"","执勤时段":""},{"岗位编号":14,"姓名":"李京泽","职务":"民警","电话":"18518857856","电台":"","执勤时段":""},{"岗位编号":15,"姓名":"段成军","职务":"民警","电话":"18518855756","电台":"","执勤时段":""},{"岗位编号":16,"姓名":"何磊","职务":"民警","电话":"18518856394","电台":"","执勤时段":""},{"岗位编号":17,"姓名":"郭根立","职务":"民警","电话":"18518857713","电台":"","执勤时段":""},{"岗位编号":18,"姓名":"姚保华","职务":"民警","电话":"18518857015","电台":"","执勤时段":""},{"岗位编号":18,"姓名":"谢诤","职务":"民警","电话":"18518855631","电台":"","执勤时段":""},{"岗位编号":25,"姓名":"石守军","职务":"民警","电话":"19810259371","电台":"","执勤时段":""},{"岗位编号":26,"姓名":"张小永、张庚金","职务":"民警","电话":"19810255722/19810255707","电台":"","执勤时段":""},{"岗位编号":26,"姓名":"王涛","职务":"民警","电话":"19810258068","电台":"","执勤时段":""},{"岗位编号":19,"姓名":"马辉","职务":"所长","电话":"19810259056","电台":"","执勤时段":""},{"岗位编号":19,"姓名":"李克","职务":"社区队长","电话":"19810260064","电台":"","执勤时段":""},{"岗位编号":20,"姓名":"刘斌","职务":"打击队长","电话":"19810259070","电台":"","执勤时段":""},{"岗位编号":20,"姓名":"张亮","职务":"综合指挥室副主任","电话":"19810255086","电台":"","执勤时段":""},{"岗位编号":21,"姓名":"蔡长军","职务":"民警","电话":"19810259018","电台":"","执勤时段":""},{"岗位编号":21,"姓名":"黄志强","职务":"民警","电话":"19810259012","电台":"","执勤时段":""},{"岗位编号":22,"姓名":"张建华","职务":"民警","电话":"19810259018","电台":"","执勤时段":""},{"岗位编号":22,"姓名":"赵新宇","职务":"民警","电话":"19810255087","电台":"","执勤时段":""},{"岗位编号":23,"姓名":"韩腾飞","职务":"民警","电话":"19810255124","电台":"","执勤时段":""},{"岗位编号":24,"姓名":"王兆纯","职务":"民警","电话":"19810255106","电台":"","执勤时段":""}]